intelecom/__init__.py
intelecom/intelecom.py
intelecom-0.0.8.dist-info/LICENSE
intelecom-0.0.8.dist-info/METADATA
intelecom-0.0.8.dist-info/WHEEL
intelecom-0.0.8.dist-info/top_level.txt
intelecom-0.0.8.dist-info/RECORD
